tree_sitter/__init__.py
tree_sitter/__init__.pyi
tree_sitter/_binding.cp310-win_arm64.pyd
tree_sitter/py.typed
tree_sitter-0.25.1.dist-info/licenses/LICENSE
tree_sitter-0.25.1.dist-info/METADATA
tree_sitter-0.25.1.dist-info/WHEEL
tree_sitter-0.25.1.dist-info/top_level.txt
tree_sitter-0.25.1.dist-info/RECORD
