Metadata-Version: 2.1
Name: tree-sitter
Version: 0.25.1
Summary: Python bindings to the Tree-sitter parsing library
Author-email: Max Brunsfeld <maxbrunsfeld@gmail.com>
Project-URL: Homepage, https://tree-sitter.github.io/tree-sitter/
Project-URL: Source, https://github.com/tree-sitter/py-tree-sitter
Project-URL: Documentation, https://tree-sitter.github.io/py-tree-sitter/
Project-URL: Discord, https://discord.gg/w7nTvsVJhm
Project-URL: Matrix, https://matrix.to/#/#tree-sitter-chat:matrix.org
Keywords: incremental,parsing,tree-sitter
Classifier: Intended Audience :: Developers
Classifier: License :: OSI Approved :: MIT License
Classifier: Operating System :: OS Independent
Classifier: Programming Language :: C
Classifier: Programming Language :: Python
Classifier: Topic :: Software Development :: Compilers
Classifier: Topic :: Text Processing :: Linguistic
Classifier: Typing :: Typed
Requires-Python: >=3.10
Provides-Extra: docs
Provides-Extra: tests
License-File: LICENSE
